AUTHORS.rst
CHANGELOG.rst
LICENSE
MANIFEST.in
README.rst
setup.py
jmbo_post.egg-info/PKG-INFO
jmbo_post.egg-info/SOURCES.txt
jmbo_post.egg-info/dependency_links.txt
jmbo_post.egg-info/not-zip-safe
jmbo_post.egg-info/requires.txt
jmbo_post.egg-info/top_level.txt
post/__init__.py
post/admin.py
post/models.py
post/urls.py
post/api/__init__.py
post/fixtures/photosizes.json
post/locale/af/LC_MESSAGES/django.mo
post/locale/af/LC_MESSAGES/django.po
post/locale/fr/LC_MESSAGES/django.mo
post/locale/fr/LC_MESSAGES/django.po
post/migrations/0001_initial.py
post/migrations/0002_post_markup.py
post/migrations/0003_remove_post_content.py
post/migrations/__init__.py
post/templates/post/inclusion_tags/post_detail.html
post/tests/__init__.py
post/tests/__init__.pyc
post/tests/manage.py
post/tests/test_admin.py
post/tests/test_admin.pyc
post/tests/test_api.py
post/tests/test_views.py
post/tests/test_views.pyc
post/tests/urls.py
post/tests/urls.pyc
post/tests/requirements/111.txt
post/tests/requirements/19.txt
post/tests/settings/111.py
post/tests/settings/19.py
post/tests/settings/19.pyc
post/tests/settings/__init__.py
post/tests/settings/__init__.pyc
post/tests/templates/base.html