Metadata-Version: 1.1
Name: jmbo-post
Version: 3.0.0
Summary: Jmbo post application. Post is a synonym for article. It is the most common content type.
Home-page: http://github.com/praekelt/jmbo-post
Author: Praekelt Consulting
Author-email: dev@praekelt.com
License: BSD
Platform: UNKNOWN
Classifier: Programming Language :: Python
Classifier: License :: OSI Approved :: BSD License
Classifier: Development Status :: 5 - Production/Stable
Classifier: Operating System :: OS Independent
Classifier: Framework :: Django
Classifier: Intended Audience :: Developers
Classifier: Topic :: Internet :: WWW/HTTP :: Dynamic Content
